messlidger/__init__.py
messlidger/__main__.py
messlidger/client.py
messlidger/command.py
messlidger/config.py
messlidger/contact.py
messlidger/gateway.py
messlidger/group.py
messlidger/session.py
messlidger/util.py
messlidger-0.2.1.dist-info/licenses/LICENSE
messlidger-0.2.1.dist-info/METADATA
messlidger-0.2.1.dist-info/WHEEL
messlidger-0.2.1.dist-info/entry_points.txt
messlidger-0.2.1.dist-info/top_level.txt
messlidger-0.2.1.dist-info/RECORD
