Metadata-Version: 2.4
Name: messlidger
Version: 0.2.1
Summary: A Facebook Messenger/XMPP gateway
Author-email: Nicolas Cedilnik <nicoco@nicoco.fr>
License-Expression: AGPL-3.0-or-later
Project-URL: Homepage, https://codeberg.org/slidge/messlidger
Project-URL: Issues, https://codeberg.org/slidge/messlidger/issues
Project-URL: Repository, https://codeberg.org/slidge/messlidger
Project-URL: Chat room, https://slidge.im/xmpp-web/#/guest?join=slidge@conference.nicoco.fr
Project-URL: Documentation, https://slidge.im/docs/messlidger/main
Project-URL: changelog, https://codeberg.org/slidge/messlidger/releases
Keywords: xmpp,gateway,bridge,instant messaging,chat,facebook messenger
Classifier: Topic :: Internet :: XMPP
Requires-Python: >=3.11
License-File: LICENSE
Requires-Dist: mautrix-facebook<0.6,>=0.5.0
Requires-Dist: slidge<0.3,>=0.2.0a3
Dynamic: license-file
